Metadata-Version: 2.1
Name: rai-distributions
Version: 0.1
Summary: Gaussian distributions
Home-page: UNKNOWN
Author: Santos Rai
License: UNKNOWN
Platform: UNKNOWN
